midas_dev/__init__.py
midas_dev/common_pyproject.toml
midas_dev/deploy.py
midas_dev/deploy_data/health_alarm_notify.conf
midas_dev/deploy_data/health_alarm_notify.source.conf
midas_dev/deploy_data/netdata_python_custom_sender.py
midas_dev/main.py
midas_dev/utils.py
midas_dev-0.48.0.dist-info/entry_points.txt
midas_dev-0.48.0.dist-info/METADATA
midas_dev-0.48.0.dist-info/WHEEL
midas_dev-0.48.0.dist-info/LICENSE
midas_dev-0.48.0.dist-info/RECORD
