Metadata-Version: 2.1
Name: midas-dev
Version: 0.48.0
Summary: 
Author: Anton V
Author-email: anton.vasilyev@midas.investments
Requires-Python: >=3.10,<4.0
Classifier: Programming Language :: Python :: 3
Classifier: Programming Language :: Python :: 3.10
Classifier: Programming Language :: Python :: 3.11
Provides-Extra: django
Requires-Dist: autoflake (>=1.7.8,<2.0.0)
Requires-Dist: black (>=22.10.0,<23.0.0)
Requires-Dist: click (>=8.1.3,<9.0.0)
Requires-Dist: coloredlogs (>=15.0.1,<16.0.0)
Requires-Dist: django-coverage-plugin (>=2.0.4,<3.0.0) ; extra == "django"
Requires-Dist: django-debug-toolbar (>=3.7.0,<4.0.0) ; extra == "django"
Requires-Dist: django-extra-checks (>=0.13.3,<0.14.0) ; extra == "django"
Requires-Dist: django-migration-linter (>=4.1.0,<5.0.0) ; extra == "django"
Requires-Dist: django-querycount (>=0.7.0,<0.8.0) ; extra == "django"
Requires-Dist: django-split-settings (>=1.2.0,<2.0.0) ; extra == "django"
Requires-Dist: django-stubs (>=1.13.0,<2.0.0) ; extra == "django"
Requires-Dist: django-stubs-ext (>=0.7.0,<0.8.0) ; extra == "django"
Requires-Dist: django-test-migrations (>=1.2.0,<2.0.0) ; extra == "django"
Requires-Dist: flake8 (>=5.0.4,<6.0.0)
Requires-Dist: flake8-broken-line (>=0.6.0,<0.7.0)
Requires-Dist: flake8-debugger (>=4.1.2,<5.0.0)
Requires-Dist: flake8-django (>=1.1.5,<2.0.0) ; extra == "django"
Requires-Dist: flake8-mock-x2 (>=0.4.1,<0.5.0)
Requires-Dist: flake8-print (>=5.0.0,<6.0.0)
Requires-Dist: flake8-pytest-style (>=1.6.0,<2.0.0)
Requires-Dist: flake8-use-fstring (>=1.4,<2.0)
Requires-Dist: ipdb (>=0.13.9,<0.14.0)
Requires-Dist: isort (>=5.10.1,<6.0.0)
Requires-Dist: mypy (>=0.991,<0.992)
Requires-Dist: poetry (>=1.2.2,<2.0.0)
Requires-Dist: poetryup (>=0.12.5,<0.13.0)
Requires-Dist: pre-commit (>=2.20.0,<3.0.0)
Requires-Dist: pytest (>=7.2.0,<8.0.0)
Requires-Dist: pytest-asyncio (>=0.20.2,<0.21.0)
Requires-Dist: pytest-blockage (>=0.2.4,<0.3.0)
Requires-Dist: pytest-cov (>=4.0.0,<5.0.0)
Requires-Dist: pytest-deadfixtures (>=2.2.1,<3.0.0)
Requires-Dist: pytest-django (>=4.5.2,<5.0.0) ; extra == "django"
Requires-Dist: pytest-env (>=0.8.1,<0.9.0)
Requires-Dist: pytest-timeout (>=2.1.0,<3.0.0)
Requires-Dist: toml (>=0.10.2,<0.11.0)
